{
    "character": "bob richards",
    "stanceList" : [],
    "version": "7.000v",
    "skill": {
        "RageArt": {
            "number": 1,
            "name_en": "Rage Art",
            "stance" : "",
            "command": "(레이지도중) .3 12",
            "hitPosition": "M",
            "damage": 55,
            "frame": 20,
            "hitFrame": "",
            "counterHitFrame": "",
            "blockedFrame": "",
            "screw": false,
            "powercrash": false,
            "homing": false,
            "wallBound": false,
            "wallBreak": false,
            "floorBreak": false
        },
        "RageDrive": {
            "number": 2,
            "name_en": "Rage Drive",
            "stance" : "",
            "command": "(레이지도중) .6 23 .6+",
            "hitPosition": "MM",
            "damage": 43,
            "frame": 26,
            "hitFrame": "",
            "counterHitFrame": "",
            "blockedFrame": "",
            "screw": false,
            "powercrash": false,
            "homing": false,
            "wallBound": false,
            "wallBreak": false,
            "floorBreak": false
        },
        "StraigthRandel": {
            "number": 3,
            "name_en": "Straight Randel",
            "stance" : "",
            "command": "1 1 2",
            "hitPosition": "HHH",
            "damage": 24,
            "frame": 10,
            "hitFrame": "",
            "counterHitFrame": "",
            "blockedFrame": "",
            "screw": false,
            "powercrash": false,
            "homing": false,
            "wallBound": false,
            "wallBreak": false,
            "floorBreak": false
        },
        "OneTwoPunch": {
            "number": 4,
            "name_en": "One Two Punch",
            "stance" : "",
            "command": "1 2",
            "hitPosition": "HH",
            "damage": 17,
            "frame": 10,
            "hitFrame": "",
            "counterHitFrame": "",
            "blockedFrame": "",
            "screw": false,
            "powercrash": false,
            "homing": false,
            "wallBound": false,
            "wallBreak": false,
            "floorBreak": false
        },
        "FastBreak": {
            "number": 5,
            "name_en": "Fast Break",
            "stance" : "",
            "command": "1 2 12",
            "hitPosition": "HHM",
            "damage": 37,
            "frame": 10,
            "hitFrame": "",
            "counterHitFrame": "",
            "blockedFrame": "",
            "screw": false,
            "powercrash": false,
            "homing": false,
            "wallBound": false,
            "wallBreak": false,
            "floorBreak": false
        },
        "CoursePicante": {
            "number": 6,
            "name_en": "Course Picante",
            "stance" : "",
            "command": "1 3 3",
            "hitPosition": "HLM",
            "damage": 35,
            "frame": 10,
            "hitFrame": "",
            "counterHitFrame": "",
            "blockedFrame": "",
            "screw": false,
            "powercrash": false,
            "homing": false,
            "wallBound": false,
            "wallBreak": false,
            "floorBreak": false
        },
        "CourseSarat": {
            "number": 7,
            "name_en": "Course Sarat",
            "stance" : "",
            "command": "1 4",
            "hitPosition": "HH",
            "damage": 22,
            "frame": 10,
            "hitFrame": "",
            "counterHitFrame": "",
            "blockedFrame": "",
            "screw": false,
            "powercrash": false,
            "homing": false,
            "wallBound": false,
            "wallBreak": false,
            "floorBreak": false
        },
        "CourseAchuto": {
            "number": 8,
            "name_en": "Course Achuto",
            "stance" : "",
            "command": "1 .2 4",
            "hitPosition": "HL",
            "damage": 20,
            "frame": 10,
            "hitFrame": "",
            "counterHitFrame": "",
            "blockedFrame": "",
            "screw": false,
            "powercrash": false,
            "homing": false,
            "wallBound": false,
            "wallBreak": false,
            "floorBreak": false
        },
        "BaristaSwirl": {
            "number": 9,
            "name_en": "Barista Swirl",
            "stance" : "",
            "command": "2 1 4",
            "hitPosition": "HMM",
            "damage": 38,
            "frame": 10,
            "hitFrame": "",
            "counterHitFrame": "",
            "blockedFrame": "",
            "screw": false,
            "powercrash": false,
            "homing": false,
            "wallBound": false,
            "wallBreak": false,
            "floorBreak": false
        },
        "Croque-Monsieur": {
            "number": 10,
            "name_en": "Croque-Monsieur",
            "stance" : "",
            "command": "3 4",
            "hitPosition": "HM",
            "damage": 31,
            "frame": 18,
            "hitFrame": "",
            "counterHitFrame": "",
            "blockedFrame": "",
            "screw": false,
            "powercrash": false,
            "homing": false,
            "wallBound": false,
            "wallBreak": false,
            "floorBreak": false
        },
        "SparklingHop": {
            "number": 11,
            "name_en": "Sparkling Hop",
            "stance" : "",
            "command": "4 3 34",
            "hitPosition": "HMM",
            "damage": 27,
            "frame": 13,
            "hitFrame": "",
            "counterHitFrame": "",
            "blockedFrame": "",
            "screw": false,
            "powercrash": false,
            "homing": false,
            "wallBound": false,
            "wallBreak": false,
            "floorBreak": false
        },
        "BlackPoêlé": {
            "number": 12,
            "name_en": "Black Poêlé",
            "stance" : "",
            "command": "12 12",
            "hitPosition": "MM",
            "damage": 38,
            "frame": 19,
            "hitFrame": "",
            "counterHitFrame": "",
            "blockedFrame": "",
            "screw": false,
            "powercrash": false,
            "homing": false,
            "wallBound": false,
            "wallBreak": false,
            "floorBreak": false
        },
        "CircleWhopper": {
            "number": 13,
            "name_en": "Circle Whopper",
            "stance" : "",
            "command": ".6 2 3",
            "hitPosition": "HM",
            "damage": 32,
            "frame": 12,
            "hitFrame": "",
            "counterHitFrame": "",
            "blockedFrame": "",
            "screw": false,
            "powercrash": false,
            "homing": false,
            "wallBound": false,
            "wallBreak": false,
            "floorBreak": false
        },
        "MerguezKickCombo": {
            "number": 14,
            "name_en": "Merguez Kick Combo",
            "stance" : "",
            "command": ".6 3 4",
            "hitPosition": "MM",
            "damage": 41,
            "frame": 21,
            "hitFrame": "",
            "counterHitFrame": "",
            "blockedFrame": "",
            "screw": false,
            "powercrash": false,
            "homing": false,
            "wallBound": false,
            "wallBreak": false,
            "floorBreak": false
        },
        "SpinningLinguine": {
            "number": 15,
            "name_en": "Spinning Linguine",
            "stance" : "",
            "command": ".6 4",
            "hitPosition": "H",
            "damage": 20,
            "frame": 16,
            "hitFrame": "",
            "counterHitFrame": "",
            "blockedFrame": "",
            "screw": false,
            "powercrash": false,
            "homing": false,
            "wallBound": false,
            "wallBreak": false,
            "floorBreak": false
        },
        "GigaJacker": {
            "number": 16,
            "name_en": "Giga Jacker",
            "stance" : "",
            "command": ".6 12",
            "hitPosition": "M",
            "damage": 25,
            "frame": 15,
            "hitFrame": "",
            "counterHitFrame": "",
            "blockedFrame": "",
            "screw": false,
            "powercrash": false,
            "homing": false,
            "wallBound": false,
            "wallBreak": false,
            "floorBreak": false
        },
        "SpinnerBall": {
            "number": 17,
            "name_en": "Spinner Ball",
            "stance" : "",
            "command": ".6 34",
            "hitPosition": "",
            "damage": 9,
            "frame": -1,
            "hitFrame": "",
            "counterHitFrame": "",
            "blockedFrame": "",
            "screw": false,
            "powercrash": false,
            "homing": false,
            "wallBound": false,
            "wallBreak": false,
            "floorBreak": false
        },
        "LyonnaiseBreak": {
            "number": 18,
            "name_en": "Lyonnaise Break",
            "stance" : "",
            "command": "(During Spinner Ball) 1",
            "hitPosition": "M",
            "damage": 18,
            "frame": 44,
            "hitFrame": "",
            "counterHitFrame": "",
            "blockedFrame": "",
            "screw": false,
            "powercrash": false,
            "homing": false,
            "wallBound": false,
            "wallBreak": false,
            "floorBreak": false
        },
        "GaletteSlicer": {
            "number": 19,
            "name_en": "Galette Slicer",
            "stance" : "",
            "command": "(During Spinner Ball) 2",
            "hitPosition": "M",
            "damage": 21,
            "frame": 48,
            "hitFrame": "",
            "counterHitFrame": "",
            "blockedFrame": "",
            "screw": false,
            "powercrash": false,
            "homing": false,
            "wallBound": false,
            "wallBreak": false,
            "floorBreak": false
        },
        "SnailKick": {
            "number": 20,
            "name_en": "Snail Kick",
            "stance" : "",
            "command": "(During Spinner Ball) 3",
            "hitPosition": "H",
            "damage": 30,
            "frame": 45,
            "hitFrame": "",
            "counterHitFrame": "",
            "blockedFrame": "",
            "screw": false,
            "powercrash": false,
            "homing": false,
            "wallBound": false,
            "wallBreak": false,
            "floorBreak": false
        },
        "StealingHome": {
            "number": 21,
            "name_en": "Stealing Home",
            "stance" : "",
            "command": "(During Spinner Ball) 4",
            "hitPosition": "L",
            "damage": 14,
            "frame": 48,
            "hitFrame": "",
            "counterHitFrame": "",
            "blockedFrame": "",
            "screw": false,
            "powercrash": false,
            "homing": false,
            "wallBound": false,
            "wallBreak": false,
            "floorBreak": false
        },
        "PerfectPress": {
            "number": 22,
            "name_en": "Perfect Press",
            "stance" : "",
            "command": "(During Spinner Ball) 34",
            "hitPosition": "M",
            "damage": 28,
            "frame": 54,
            "hitFrame": "",
            "counterHitFrame": "",
            "blockedFrame": "",
            "screw": false,
            "powercrash": false,
            "homing": false,
            "wallBound": false,
            "wallBreak": false,
            "floorBreak": false
        },
        "EscalopeElbow": {
            "number": 23,
            "name_en": "Escalope Elbow",
            "stance" : "",
            "command": ".3 1 2",
            "hitPosition": "MM",
            "damage": 28,
            "frame": 14,
            "hitFrame": "",
            "counterHitFrame": "",
            "blockedFrame": "",
            "screw": false,
            "powercrash": false,
            "homing": false,
            "wallBound": false,
            "wallBreak": false,
            "floorBreak": false
        },
        "SlashDarne": {
            "number": 24,
            "name_en": "Slash Darne",
            "stance" : "",
            "command": ".3 2",
            "hitPosition": "M",
            "damage": 14,
            "frame": 15,
            "hitFrame": "",
            "counterHitFrame": "",
            "blockedFrame": "",
            "screw": false,
            "powercrash": false,
            "homing": false,
            "wallBound": false,
            "wallBreak": false,
            "floorBreak": false
        },
        "GaufrettesCutter": {
            "number": 25,
            "name_en": "Gaufrettes Cutter",
            "stance" : "",
            "command": ".3 3 1 1",
            "hitPosition": "MHM",
            "damage": 42,
            "frame": 18,
            "hitFrame": "",
            "counterHitFrame": "",
            "blockedFrame": "",
            "screw": false,
            "powercrash": false,
            "homing": false,
            "wallBound": false,
            "wallBreak": false,
            "floorBreak": false
        },
        "GaufrettesPunch": {
            "number": 26,
            "name_en": "Gaufrettes Punch",
            "stance" : "",
            "command": ".3 3 2",
            "hitPosition": "MH",
            "damage": 34,
            "frame": 18,
            "hitFrame": "",
            "counterHitFrame": "",
            "blockedFrame": "",
            "screw": false,
            "powercrash": false,
            "homing": false,
            "wallBound": false,
            "wallBreak": false,
            "floorBreak": false
        },
        "GaufrettesKick": {
            "number": 27,
            "name_en": "Gaufrettes Kick",
            "stance" : "",
            "command": ".3 3 4",
            "hitPosition": "MLH",
            "damage": 40,
            "frame": 18,
            "hitFrame": "",
            "counterHitFrame": "",
            "blockedFrame": "",
            "screw": false,
            "powercrash": false,
            "homing": false,
            "wallBound": false,
            "wallBreak": false,
            "floorBreak": false
        },
        "RunnerFlip": {
            "number": 28,
            "name_en": "Runner Flip",
            "stance" : "",
            "command": ".3 34 4",
            "hitPosition": "MMM",
            "damage": 28,
            "frame": 18,
            "hitFrame": "",
            "counterHitFrame": "",
            "blockedFrame": "",
            "screw": false,
            "powercrash": false,
            "homing": false,
            "wallBound": false,
            "wallBreak": false,
            "floorBreak": false
        },
        "CoupéChop": {
            "number": 29,
            "name_en": "Coupé Chop",
            "stance" : "",
            "command": ".2 1",
            "hitPosition": "M",
            "damage": 18,
            "frame": 18,
            "hitFrame": "",
            "counterHitFrame": "",
            "blockedFrame": "",
            "screw": false,
            "powercrash": false,
            "homing": false,
            "wallBound": false,
            "wallBreak": false,
            "floorBreak": false
        },
        "CombinationMince": {
            "number": 30,
            "name_en": "Combination Mince",
            "stance" : "",
            "command": ".2 2 1 2 2",
            "hitPosition": "MMMM",
            "damage": 65,
            "frame": 15,
            "hitFrame": "",
            "counterHitFrame": "",
            "blockedFrame": "",
            "screw": false,
            "powercrash": false,
            "homing": false,
            "wallBound": false,
            "wallBreak": false,
            "floorBreak": false
        },
        "CombinationBle": {
            "number": 31,
            "name_en": "Combination Ble",
            "stance" : "",
            "command": ".2 2 3",
            "hitPosition": "MM",
            "damage": 33,
            "frame": 15,
            "hitFrame": "",
            "counterHitFrame": "",
            "blockedFrame": "",
            "screw": false,
            "powercrash": false,
            "homing": false,
            "wallBound": false,
            "wallBreak": false,
            "floorBreak": false
        },
        "CombinationBaldo": {
            "number": 32,
            "name_en": "Combination Baldo",
            "stance" : "",
            "command": ".2 2 4",
            "hitPosition": "MM",
            "damage": 33,
            "frame": 15,
            "hitFrame": "",
            "counterHitFrame": "",
            "blockedFrame": "",
            "screw": false,
            "powercrash": false,
            "homing": false,
            "wallBound": false,
            "wallBreak": false,
            "floorBreak": false
        },
        "PaniniSweep": {
            "number": 33,
            "name_en": "Panini Sweep",
            "stance" : "",
            "command": ".2 3 4",
            "hitPosition": "LH",
            "damage": 34,
            "frame": 19,
            "hitFrame": "",
            "counterHitFrame": "",
            "blockedFrame": "",
            "screw": false,
            "powercrash": false,
            "homing": false,
            "wallBound": false,
            "wallBreak": false,
            "floorBreak": false
        },
        "TornadoMixer": {
            "number": 34,
            "name_en": "Tornado Mixer",
            "stance" : "",
            "command": ".2 4 3 4",
            "hitPosition": "LHM",
            "damage": 50,
            "frame": 16,
            "hitFrame": "",
            "counterHitFrame": "",
            "blockedFrame": "",
            "screw": false,
            "powercrash": false,
            "homing": false,
            "wallBound": false,
            "wallBreak": false,
            "floorBreak": false
        },
        "ApiciusSpecial": {
            "number": 35,
            "name_en": "Apicius Special",
            "stance" : "",
            "command": ".2 12 2 1",
            "hitPosition": "HHMH",
            "damage": 35,
            "frame": 14,
            "hitFrame": "",
            "counterHitFrame": "",
            "blockedFrame": "",
            "screw": false,
            "powercrash": false,
            "homing": false,
            "wallBound": false,
            "wallBreak": false,
            "floorBreak": false
        },
        "DuckFlip": {
            "number": 36,
            "name_en": "Duck Flip",
            "stance" : "",
            "command": ".2 34",
            "hitPosition": "MM",
            "damage": 26,
            "frame": 15,
            "hitFrame": "",
            "counterHitFrame": "",
            "blockedFrame": "",
            "screw": false,
            "powercrash": false,
            "homing": false,
            "wallBound": false,
            "wallBreak": false,
            "floorBreak": false
        },
        "BiteUppercut": {
            "number": 37,
            "name_en": "Bite Uppercut",
            "stance" : "",
            "command": ".1 2",
            "hitPosition": "M",
            "damage": 17,
            "frame": 14,
            "hitFrame": "",
            "counterHitFrame": "",
            "blockedFrame": "",
            "screw": false,
            "powercrash": false,
            "homing": false,
            "wallBound": false,
            "wallBreak": false,
            "floorBreak": false
        },
        "LiaisonSpike": {
            "number": 38,
            "name_en": "Liaison Spike",
            "stance" : "",
            "command": ".1 3",
            "hitPosition": "L",
            "damage": 17,
            "frame": 20,
            "hitFrame": "",
            "counterHitFrame": "",
            "blockedFrame": "",
            "screw": false,
            "powercrash": false,
            "homing": false,
            "wallBound": false,
            "wallBreak": false,
            "floorBreak": false
        },
        "ContornoFarce": {
            "number": 39,
            "name_en": "Contorno Farce",
            "stance" : "",
            "command": ".1 4 4 3 3",
            "hitPosition": "LMHM",
            "damage": 59,
            "frame": 24,
            "hitFrame": "",
            "counterHitFrame": "",
            "blockedFrame": "",
            "screw": false,
            "powercrash": false,
            "homing": false,
            "wallBound": false,
            "wallBreak": false,
            "floorBreak": false
        },
        "ContornoMist": {
            "number": 40,
            "name_en": "Contorno Mist",
            "stance" : "",
            "command": ".1 4 4 4",
            "hitPosition": "LML",
            "damage": 29,
            "frame": 24,
            "hitFrame": "",
            "counterHitFrame": "",
            "blockedFrame": "",
            "screw": false,
            "powercrash": false,
            "homing": false,
            "wallBound": false,
            "wallBreak": false,
            "floorBreak": false
        },
        "AbatsSnipe": {
            "number": 41,
            "name_en": "Abats Snipe",
            "stance" : "",
            "command": ".1 12",
            "hitPosition": "M",
            "damage": 16,
            "frame": 18,
            "hitFrame": "",
            "counterHitFrame": "",
            "blockedFrame": "",
            "screw": false,
            "powercrash": false,
            "homing": false,
            "wallBound": false,
            "wallBreak": false,
            "floorBreak": false
        },
        "HuileSlip": {
            "number": 42,
            "name_en": "Huile Slip",
            "stance" : "",
            "command": ".1 34 4",
            "hitPosition": "LL",
            "damage": 26,
            "frame": 19,
            "hitFrame": "",
            "counterHitFrame": "",
            "blockedFrame": "",
            "screw": false,
            "powercrash": false,
            "homing": false,
            "wallBound": false,
            "wallBreak": false,
            "floorBreak": false
        },
        "Ravenous": {
            "number": 43,
            "name_en": "Ravenous",
            "stance" : "",
            "command": ".4 1 2",
            "hitPosition": "MM",
            "damage": 31,
            "frame": 17,
            "hitFrame": "",
            "counterHitFrame": "",
            "blockedFrame": "",
            "screw": false,
            "powercrash": false,
            "homing": false,
            "wallBound": false,
            "wallBreak": false,
            "floorBreak": false
        },
        "CombinationBitter": {
            "number": 44,
            "name_en": "Combination Bitter",
            "stance" : "",
            "command": ".4 2 2 4 4",
            "hitPosition": "MHMH",
            "damage": 58,
            "frame": 13,
            "hitFrame": "",
            "counterHitFrame": "",
            "blockedFrame": "",
            "screw": false,
            "powercrash": false,
            "homing": false,
            "wallBound": false,
            "wallBreak": false,
            "floorBreak": false
        },
        "WhoppingKick": {
            "number": 45,
            "name_en": "Whopping Kick",
            "stance" : "",
            "command": ".4 3",
            "hitPosition": "M",
            "damage": 20,
            "frame": 17,
            "hitFrame": "",
            "counterHitFrame": "",
            "blockedFrame": "",
            "screw": false,
            "powercrash": false,
            "homing": false,
            "wallBound": false,
            "wallBreak": false,
            "floorBreak": false
        },
        "PretzelCrush": {
            "number": 46,
            "name_en": "Pretzel Crush",
            "stance" : "",
            "command": ".4 4 1",
            "hitPosition": "MM",
            "damage": 32,
            "frame": 15,
            "hitFrame": "",
            "counterHitFrame": "",
            "blockedFrame": "",
            "screw": false,
            "powercrash": false,
            "homing": false,
            "wallBound": false,
            "wallBreak": false,
            "floorBreak": false
        },
        "CombinationBittersweet": {
            "number": 47,
            "name_en": "Combination Bittersweet",
            "stance" : "",
            "command": ".4 4 4",
            "hitPosition": "MH",
            "damage": 35,
            "frame": 15,
            "hitFrame": "",
            "counterHitFrame": "",
            "blockedFrame": "",
            "screw": false,
            "powercrash": false,
            "homing": false,
            "wallBound": false,
            "wallBreak": false,
            "floorBreak": false
        },
        "ThreeStarCombo": {
            "number": 48,
            "name_en": "Three Star Combo",
            "stance" : "",
            "command": ".4 12 1 2",
            "hitPosition": "MMH",
            "damage": 50,
            "frame": 17,
            "hitFrame": "",
            "counterHitFrame": "",
            "blockedFrame": "",
            "screw": false,
            "powercrash": false,
            "homing": false,
            "wallBound": false,
            "wallBreak": false,
            "floorBreak": false
        },
        "ReverseSpinnerBall": {
            "number": 49,
            "name_en": "Reverse Spinner Ball",
            "stance" : "",
            "command": ".4 34",
            "hitPosition": "",
            "damage": 0,
            "frame": -1,
            "hitFrame": "",
            "counterHitFrame": "",
            "blockedFrame": "",
            "screw": false,
            "powercrash": false,
            "homing": false,
            "wallBound": false,
            "wallBreak": false,
            "floorBreak": false
        },
        "ReverseDuckFlip": {
            "number": 50,
            "name_en": "Reverse Duck Flip",
            "stance" : "",
            "command": ".7 3",
            "hitPosition": "MM",
            "damage": 28,
            "frame": 15,
            "hitFrame": "",
            "counterHitFrame": "",
            "blockedFrame": "",
            "screw": false,
            "powercrash": false,
            "homing": false,
            "wallBound": false,
            "wallBreak": false,
            "floorBreak": false
        },
        "EggBound": {
            "number": 51,
            "name_en": "Egg Bound",
            "stance" : "",
            "command": ".8 12",
            "hitPosition": "",
            "damage": 0,
            "frame": -1,
            "hitFrame": "",
            "counterHitFrame": "",
            "blockedFrame": "",
            "screw": false,
            "powercrash": false,
            "homing": false,
            "wallBound": false,
            "wallBreak": false,
            "floorBreak": false
        },
        "HatchingPunch": {
            "number": 52,
            "name_en": "Hatching Punch",
            "stance" : "",
            "command": ".8 12 1",
            "hitPosition": "M",
            "damage": 21,
            "frame": 28,
            "hitFrame": "",
            "counterHitFrame": "",
            "blockedFrame": "",
            "screw": false,
            "powercrash": false,
            "homing": false,
            "wallBound": false,
            "wallBreak": false,
            "floorBreak": false
        },
        "Strainer": {
            "number": 53,
            "name_en": "Strainer",
            "stance" : "",
            "command": ".8 34",
            "hitPosition": "M",
            "damage": 20,
            "frame": 24,
            "hitFrame": "",
            "counterHitFrame": "",
            "blockedFrame": "",
            "screw": false,
            "powercrash": false,
            "homing": false,
            "wallBound": false,
            "wallBreak": false,
            "floorBreak": false
        },
        "FlyingJambon": {
            "number": 54,
            "name_en": "Flying Jambon",
            "stance" : "",
            "command": ".9 3",
            "hitPosition": "M",
            "damage": 20,
            "frame": 20,
            "hitFrame": "",
            "counterHitFrame": "",
            "blockedFrame": "",
            "screw": false,
            "powercrash": false,
            "homing": false,
            "wallBound": false,
            "wallBreak": false,
            "floorBreak": false
        },
        "FaisanCrow": {
            "number": 55,
            "name_en": "Faisan Crow",
            "stance" : "",
            "command": ".9 4 4",
            "hitPosition": "MM",
            "damage": 32,
            "frame": 25,
            "hitFrame": "",
            "counterHitFrame": "",
            "blockedFrame": "",
            "screw": false,
            "powercrash": false,
            "homing": false,
            "wallBound": false,
            "wallBreak": false,
            "floorBreak": false
        },
        "CrackerTariata": {
            "number": 56,
            "name_en": "Cracker Tariata",
            "stance" : "",
            "command": ".9 12 4",
            "hitPosition": "MH",
            "damage": 35,
            "frame": 16,
            "hitFrame": "",
            "counterHitFrame": "",
            "blockedFrame": "",
            "screw": false,
            "powercrash": false,
            "homing": false,
            "wallBound": false,
            "wallBreak": false,
            "floorBreak": false
        },
        "CrackerJacker": {
            "number": 57,
            "name_en": "Cracker Jacker",
            "stance" : "",
            "command": ".9 12 12",
            "hitPosition": "MM",
            "damage": 40,
            "frame": 16,
            "hitFrame": "",
            "counterHitFrame": "",
            "blockedFrame": "",
            "screw": false,
            "powercrash": false,
            "homing": false,
            "wallBound": false,
            "wallBreak": false,
            "floorBreak": false
        },
        "RollingKebab": {
            "number": 58,
            "name_en": "Rolling Kebab",
            "stance" : "",
            "command": ".9 34 4",
            "hitPosition": "LHH",
            "damage": 42,
            "frame": 21,
            "hitFrame": "",
            "counterHitFrame": "",
            "blockedFrame": "",
            "screw": false,
            "powercrash": false,
            "homing": false,
            "wallBound": false,
            "wallBreak": false,
            "floorBreak": false
        },
        "ZipCutter": {
            "number": 59,
            "name_en": "Zip Cutter",
            "stance" : "",
            "command": ".6 .6+ 2",
            "hitPosition": "M",
            "damage": 25,
            "frame": 14,
            "hitFrame": "",
            "counterHitFrame": "",
            "blockedFrame": "",
            "screw": false,
            "powercrash": false,
            "homing": false,
            "wallBound": false,
            "wallBreak": false,
            "floorBreak": false
        },
        "JumpingBeans": {
            "number": 60,
            "name_en": "Jumping Beans",
            "stance" : "",
            "command": ".6 .6+ 3",
            "hitPosition": "M",
            "damage": 18,
            "frame": 18,
            "hitFrame": "",
            "counterHitFrame": "",
            "blockedFrame": "",
            "screw": false,
            "powercrash": false,
            "homing": false,
            "wallBound": false,
            "wallBreak": false,
            "floorBreak": false
        },
        "DoubleChapati": {
            "number": 61,
            "name_en": "Double Chapati",
            "stance" : "",
            "command": ".6 .6+ 4 4",
            "hitPosition": "MM",
            "damage": 32,
            "frame": 22,
            "hitFrame": "",
            "counterHitFrame": "",
            "blockedFrame": "",
            "screw": false,
            "powercrash": false,
            "homing": false,
            "wallBound": false,
            "wallBreak": false,
            "floorBreak": false
        },
        "HuitresCrush": {
            "number": 62,
            "name_en": "Huitres Crush",
            "stance" : "",
            "command": ".6 .6+ 34",
            "hitPosition": "MM",
            "damage": 28,
            "frame": 26,
            "hitFrame": "",
            "counterHitFrame": "",
            "blockedFrame": "",
            "screw": false,
            "powercrash": false,
            "homing": false,
            "wallBound": false,
            "wallBreak": false,
            "floorBreak": false
        },
        "HotCrossBun": {
            "number": 63,
            "name_en": "Hot Cross Bun",
            "stance" : "",
            "command": ".4 .6 1",
            "hitPosition": "M",
            "damage": 25,
            "frame": 26,
            "hitFrame": "",
            "counterHitFrame": "",
            "blockedFrame": "",
            "screw": false,
            "powercrash": false,
            "homing": false,
            "wallBound": false,
            "wallBreak": false,
            "floorBreak": false
        },
        "LangousteTail": {
            "number": 64,
            "name_en": "Langouste Tail",
            "stance" : "",
            "command": ".4 .4+",
            "hitPosition": "M",
            "damage": 20,
            "frame": 26,
            "hitFrame": "",
            "counterHitFrame": "",
            "blockedFrame": "",
            "screw": false,
            "powercrash": false,
            "homing": false,
            "wallBound": false,
            "wallBreak": false,
            "floorBreak": false
        },
        "GraterLangouste": {
            "number": 65,
            "name_en": "Grater Langouste",
            "stance" : "",
            "command": ".4 .4+ 34 (.1+ to cancel)",
            "hitPosition": "!",
            "damage": 60,
            "frame": 71,
            "hitFrame": "",
            "counterHitFrame": "",
            "blockedFrame": "",
            "screw": false,
            "powercrash": false,
            "homing": false,
            "wallBound": false,
            "wallBreak": false,
            "floorBreak": false
        },
        "GraterLangousteFeintKnuckle": {
            "number": 66,
            "name_en": "Grater Langouste Feint Knuckle",
            "stance" : "",
            "command": ".4 .4+ 34 2",
            "hitPosition": "M",
            "damage": 25,
            "frame": 57,
            "hitFrame": "",
            "counterHitFrame": "",
            "blockedFrame": "",
            "screw": false,
            "powercrash": false,
            "homing": false,
            "wallBound": false,
            "wallBreak": false,
            "floorBreak": false
        },
        "QuickLangouste": {
            "number": 67,
            "name_en": "Quick Langouste",
            "stance" : "",
            "command": ".4 .4+ 23",
            "hitPosition": "!",
            "damage": 40,
            "frame": 48,
            "hitFrame": "",
            "counterHitFrame": "",
            "blockedFrame": "",
            "screw": false,
            "powercrash": false,
            "homing": false,
            "wallBound": false,
            "wallBreak": false,
            "floorBreak": false
        },
        "LangueWasher": {
            "number": 68,
            "name_en": "Langue Washer",
            "stance" : "",
            "command": ".6 N .2 .3 1",
            "hitPosition": "H",
            "damage": 20,
            "frame": 13,
            "hitFrame": "",
            "counterHitFrame": "",
            "blockedFrame": "",
            "screw": false,
            "powercrash": false,
            "homing": false,
            "wallBound": false,
            "wallBreak": false,
            "floorBreak": false
        },
        "SpiralRocky": {
            "number": 69,
            "name_en": "Spiral Rocky",
            "stance" : "",
            "command": ".6 N .2 .3 2",
            "hitPosition": "M",
            "damage": 29,
            "frame": 16,
            "hitFrame": "",
            "counterHitFrame": "",
            "blockedFrame": "",
            "screw": false,
            "powercrash": false,
            "homing": false,
            "wallBound": false,
            "wallBreak": false,
            "floorBreak": false
        },
        "GamberoKnee": {
            "number": 70,
            "name_en": "Gambero Knee",
            "stance" : "",
            "command": ".6 N .2 .3 3 2",
            "hitPosition": "MH",
            "damage": 30,
            "frame": 16,
            "hitFrame": "",
            "counterHitFrame": "",
            "blockedFrame": "",
            "screw": false,
            "powercrash": false,
            "homing": false,
            "wallBound": false,
            "wallBreak": false,
            "floorBreak": false
        },
        "CuttingCoppa": {
            "number": 71,
            "name_en": "Cutting Coppa",
            "stance" : "",
            "command": ".6 N .2 .3 4 12",
            "hitPosition": "LM",
            "damage": 33,
            "frame": 18,
            "hitFrame": "",
            "counterHitFrame": "",
            "blockedFrame": "",
            "screw": false,
            "powercrash": false,
            "homing": false,
            "wallBound": false,
            "wallBreak": false,
            "floorBreak": false
        },
        "GranchiCanon": {
            "number": 72,
            "name_en": "Granchi Canon",
            "stance" : "",
            "command": ".6 N .2 .3 12",
            "hitPosition": "M",
            "damage": 25,
            "frame": 15,
            "hitFrame": "",
            "counterHitFrame": "",
            "blockedFrame": "",
            "screw": false,
            "powercrash": false,
            "homing": false,
            "wallBound": false,
            "wallBreak": false,
            "floorBreak": false
        },
        "PerfectSlash": {
            "number": 73,
            "name_en": "Perfect Slash",
            "stance" : "",
            "command": ".6 .6 .6 3",
            "hitPosition": "M",
            "damage": 30,
            "frame": 20,
            "hitFrame": "",
            "counterHitFrame": "",
            "blockedFrame": "",
            "screw": false,
            "powercrash": false,
            "homing": false,
            "wallBound": false,
            "wallBreak": false,
            "floorBreak": false
        },
        "SupersizeMissile": {
            "number": 74,
            "name_en": "Supersize Missile",
            "stance" : "",
            "command": ".6 .6 .6 34",
            "hitPosition": "M",
            "damage": 27,
            "frame": 26,
            "hitFrame": "",
            "counterHitFrame": "",
            "blockedFrame": "",
            "screw": false,
            "powercrash": false,
            "homing": false,
            "wallBound": false,
            "wallBreak": false,
            "floorBreak": false
        },
        "CrossButcher": {
            "number": 75,
            "name_en": "Cross Butcher",
            "stance" : "",
            "command": "(While rising) 1 2",
            "hitPosition": "MH",
            "damage": 31,
            "frame": 15,
            "hitFrame": "",
            "counterHitFrame": "",
            "blockedFrame": "",
            "screw": false,
            "powercrash": false,
            "homing": false,
            "wallBound": false,
            "wallBreak": false,
            "floorBreak": false
        },
        "HotGuimauve": {
            "number": 76,
            "name_en": "Hot Guimauve",
            "stance" : "",
            "command": "(While rising) 1 3",
            "hitPosition": "MM",
            "damage": 31,
            "frame": 15,
            "hitFrame": "",
            "counterHitFrame": "",
            "blockedFrame": "",
            "screw": false,
            "powercrash": false,
            "homing": false,
            "wallBound": false,
            "wallBreak": false,
            "floorBreak": false
        },
        "SpinachUpper": {
            "number": 77,
            "name_en": "Spinach Upper",
            "stance" : "",
            "command": "(While rising) 2 1",
            "hitPosition": "MM",
            "damage": 22,
            "frame": 14,
            "hitFrame": "",
            "counterHitFrame": "",
            "blockedFrame": "",
            "screw": false,
            "powercrash": false,
            "homing": false,
            "wallBound": false,
            "wallBreak": false,
            "floorBreak": false
        },
        "SpinachHammer": {
            "number": 78,
            "name_en": "Spinach Hammer",
            "stance" : "",
            "command": "(While rising) 2 2",
            "hitPosition": "MM",
            "damage": 30,
            "frame": 14,
            "hitFrame": "",
            "counterHitFrame": "",
            "blockedFrame": "",
            "screw": false,
            "powercrash": false,
            "homing": false,
            "wallBound": false,
            "wallBreak": false,
            "floorBreak": false
        },
        "BriocheStar": {
            "number": 79,
            "name_en": "Brioche Star",
            "stance" : "",
            "command": "(While rising) 3 34",
            "hitPosition": "HM",
            "damage": 34,
            "frame": 17,
            "hitFrame": "",
            "counterHitFrame": "",
            "blockedFrame": "",
            "screw": false,
            "powercrash": false,
            "homing": false,
            "wallBound": false,
            "wallBreak": false,
            "floorBreak": false
        },
        "RisingMatzo": {
            "number": 80,
            "name_en": "Rising Matzo",
            "stance" : "",
            "command": "(While rising) 12",
            "hitPosition": "M",
            "damage": 25,
            "frame": 15,
            "hitFrame": "",
            "counterHitFrame": "",
            "blockedFrame": "",
            "screw": false,
            "powercrash": false,
            "homing": false,
            "wallBound": false,
            "wallBreak": false,
            "floorBreak": false
        },
        "PolpoSwing": {
            "number": 81,
            "name_en": "Polpo Swing",
            "stance" : "",
            "command": "(While crouching) .3 2 1 12",
            "hitPosition": "MMM",
            "damage": 51,
            "frame": 14,
            "hitFrame": "",
            "counterHitFrame": "",
            "blockedFrame": "",
            "screw": false,
            "powercrash": false,
            "homing": false,
            "wallBound": false,
            "wallBreak": false,
            "floorBreak": false
        },
        "SeppiaSwing": {
            "number": 82,
            "name_en": "Seppia Swing",
            "stance" : "",
            "command": "(While crouching) .3 2 4 12",
            "hitPosition": "MLM",
            "damage": 51,
            "frame": 14,
            "hitFrame": "",
            "counterHitFrame": "",
            "blockedFrame": "",
            "screw": false,
            "powercrash": false,
            "homing": false,
            "wallBound": false,
            "wallBreak": false,
            "floorBreak": false
        },
        "BánhMìStrike": {
            "number": 83,
            "name_en": "Bánh mì Strike",
            "stance" : "",
            "command": "(During sidestep) 12",
            "hitPosition": "M",
            "damage": 24,
            "frame": 15,
            "hitFrame": "",
            "counterHitFrame": "",
            "blockedFrame": "",
            "screw": false,
            "powercrash": false,
            "homing": false,
            "wallBound": false,
            "wallBreak": false,
            "floorBreak": false
        },
        "PlaguePick": {
            "number": 84,
            "name_en": "Plague Pick",
            "stance" : "",
            "command": "(Back towards enemy) .2 2",
            "hitPosition": "M",
            "damage": 17,
            "frame": 15,
            "hitFrame": "",
            "counterHitFrame": "",
            "blockedFrame": "",
            "screw": false,
            "powercrash": false,
            "homing": false,
            "wallBound": false,
            "wallBreak": false,
            "floorBreak": false
        },
        "SucreTile": {
            "number": 85,
            "name_en": "Sucre Tile",
            "stance" : "",
            "command": "1234 4",
            "hitPosition": "!",
            "damage": 42,
            "frame": 72,
            "hitFrame": "",
            "counterHitFrame": "",
            "blockedFrame": "",
            "screw": false,
            "powercrash": false,
            "homing": false,
            "wallBound": false,
            "wallBreak": false,
            "floorBreak": false
        },
        "10HitCombo1": {
            "number": 86,
            "name_en": "10 Hit Combo 1",
            "stance" : "",
            "command": ".9 2 1 2 2 1 12 3 1 2 34",
            "hitPosition": "HHHMMMLMHM",
            "damage": 112,
            "frame": 20,
            "hitFrame": "",
            "counterHitFrame": "",
            "blockedFrame": "",
            "screw": false,
            "powercrash": false,
            "homing": false,
            "wallBound": false,
            "wallBreak": false,
            "floorBreak": false
        },
        "10HitCombo2": {
            "number": 87,
            "name_en": "10 Hit Combo 2",
            "stance" : "",
            "command": ".9 2 3 34 4",
            "hitPosition": "HLMMM",
            "damage": 69,
            "frame": 20,
            "hitFrame": "",
            "counterHitFrame": "",
            "blockedFrame": "",
            "screw": false,
            "powercrash": false,
            "homing": false,
            "wallBound": false,
            "wallBreak": false,
            "floorBreak": false
        },
        "QuarterDeck1": {
            "number": 88,
            "name_en": "Quarter Deck 1",
            "stance" : "",
            "command": "(상대방에 접근하며) 13",
            "hitPosition": "G",
            "damage": 35,
            "frame": 12,
            "hitFrame": "",
            "counterHitFrame": "",
            "blockedFrame": "",
            "screw": false,
            "powercrash": false,
            "homing": false,
            "wallBound": false,
            "wallBreak": false,
            "floorBreak": false
        },
        "QuarterDeck2": {
            "number": 89,
            "name_en": "Quarter Deck 2",
            "stance" : "",
            "command": "(상대방에 접근하며) .6 13",
            "hitPosition": "G",
            "damage": 35,
            "frame": 15,
            "hitFrame": "",
            "counterHitFrame": "",
            "blockedFrame": "",
            "screw": false,
            "powercrash": false,
            "homing": false,
            "wallBound": false,
            "wallBreak": false,
            "floorBreak": false
        },
        "CoolerShaker1": {
            "number": 90,
            "name_en": "Cooler Shaker 1",
            "stance" : "",
            "command": "(상대방에 접근하며) 24",
            "hitPosition": "G",
            "damage": 35,
            "frame": 12,
            "hitFrame": "",
            "counterHitFrame": "",
            "blockedFrame": "",
            "screw": false,
            "powercrash": false,
            "homing": false,
            "wallBound": false,
            "wallBreak": false,
            "floorBreak": false
        },
        "CoolerShaker2": {
            "number": 91,
            "name_en": "Cooler Shaker 2",
            "stance" : "",
            "command": "(상대방에 접근하며) .6 24",
            "hitPosition": "G",
            "damage": 35,
            "frame": 15,
            "hitFrame": "",
            "counterHitFrame": "",
            "blockedFrame": "",
            "screw": false,
            "powercrash": false,
            "homing": false,
            "wallBound": false,
            "wallBreak": false,
            "floorBreak": false
        },
        "Corkscrew": {
            "number": 92,
            "name_en": "Corkscrew",
            "stance" : "",
            "command": "(왼쪽으로부터 접근하며) 13 (or 24)",
            "hitPosition": "G",
            "damage": 40,
            "frame": 12,
            "hitFrame": "",
            "counterHitFrame": "",
            "blockedFrame": "",
            "screw": false,
            "powercrash": false,
            "homing": false,
            "wallBound": false,
            "wallBreak": false,
            "floorBreak": false
        },
        "EyeOpener": {
            "number": 93,
            "name_en": "Eye Opener",
            "stance" : "",
            "command": "(오른쪽으로부터 접근하며) 13 (or 24)",
            "hitPosition": "G",
            "damage": 40,
            "frame": 12,
            "hitFrame": "",
            "counterHitFrame": "",
            "blockedFrame": "",
            "screw": false,
            "powercrash": false,
            "homing": false,
            "wallBound": false,
            "wallBreak": false,
            "floorBreak": false
        },
        "DéglacerThrow": {
            "number": 94,
            "name_en": "Déglacer Throw",
            "stance" : "",
            "command": "(뒤에서 접근하며) 13 (or 24)",
            "hitPosition": "G",
            "damage": 50,
            "frame": 12,
            "hitFrame": "",
            "counterHitFrame": "",
            "blockedFrame": "",
            "screw": false,
            "powercrash": false,
            "homing": false,
            "wallBound": false,
            "wallBreak": false,
            "floorBreak": false
        },
        "FlyingCask": {
            "number": 95,
            "name_en": "Flying Cask",
            "stance" : "",
            "command": "(상대방에 접근하며) .6 .6+ 12",
            "hitPosition": "G",
            "damage": 30,
            "frame": 12,
            "hitFrame": "",
            "counterHitFrame": "",
            "blockedFrame": "",
            "screw": false,
            "powercrash": false,
            "homing": false,
            "wallBound": false,
            "wallBreak": false,
            "floorBreak": false
        },
        "SparklingDeath": {
            "number": 96,
            "name_en": "Sparkling Death",
            "stance" : "",
            "command": "(몸을 숙이며) .3 .2 .3+ 12",
            "hitPosition": "G",
            "damage": 30,
            "frame": 11,
            "hitFrame": "",
            "counterHitFrame": "",
            "blockedFrame": "",
            "screw": false,
            "powercrash": false,
            "homing": false,
            "wallBound": false,
            "wallBreak": false,
            "floorBreak": false
        }
    }
}